{
  "h":
  [
    {
      "n": "invokeMenuAction",
      "c": "ox",
      "p": "ek",
      "m": -1948098697
    },
    {
      "n": "setCheckClick",
      "c": "ep",
      "p": "bb",
      "m": 1
    },
    {
      "n": "setSelectedSceneTileX",
      "c": "ep",
      "p": "bv",
      "m": 1
    },
    {
      "n": "setSelectedSceneTileY",
      "c": "ep",
      "p": "bz",
      "m": 1
    },
    {
      "n": "setViewportWalking",
      "c": "ep",
      "p": "cl",
      "m": 1
    },
    {
      "n": "setSelectedSpellWidget",
      "c": "al",
      "p": "ne",
      "m": -1389002627
    },
    {
      "n": "setSelectedSpellChildIndex",
      "c": "client",
      "p": "nv",
      "m": -1574701121
    },
    {
      "n": "setSelectedSpellItemId",
      "c": "client",
      "p": "ny",
      "m": 1290431095
    },
    {
      "n": "getOldNpcOverheadArray",
      "c": "nq",
      "p": "dt",
      "m": 1
    },
    {
      "n": "getNewNpcOverheadObject",
      "c": "dl",
      "p": "ai",
      "m": 1
    },
    {
      "n": "getNewNpcOverheadArray",
      "c": "wz",
      "p": "ah",
      "m": 1
    },
    {
      "n": "getNpcOverheadMethod",
      "c": "dl",
      "p": "ao",
      "m": -727813633
    },
    {
      "n": "isMoving",
      "c": "dj",
      "p": "dj",
      "m": 1389085133
    },
    {
      "n": "getActorAnimationObject",
      "c": "dj",
      "p": "cy",
      "m": 1
    },
    {
      "n": "getActorAnimationId",
      "c": "pc",
      "p": "aj",
      "m": -576553293
    },
    {
      "n": "menuOptionsCount",
      "c": "vx",
      "p": "ah",
      "m": 1759446067
    },
    {
      "n": "menuParam0Array",
      "c": "vx",
      "p": "ae",
      "m": 1
    },
    {
      "n": "menuParam1Array",
      "c": "vx",
      "p": "az",
      "m": 1
    },
    {
      "n": "menuTypesArray",
      "c": "vx",
      "p": "aj",
      "m": 1
    },
    {
      "n": "menuIdentifiersArray",
      "c": "vx",
      "p": "ap",
      "m": 1
    },
    {
      "n": "menuItemIdsArray",
      "c": "vx",
      "p": "aa",
      "m": 1
    },
    {
      "n": "menuWorldViewIdsArray",
      "c": "vx",
      "p": "ai",
      "m": 1
    },
    {
      "n": "menuOptionsArray",
      "c": "vx",
      "p": "ad",
      "m": 1
    },
    {
      "n": "menuTargetsArray",
      "c": "vx",
      "p": "af",
      "m": 1
    }
  ]
}
